wat/__init__.py
wat/py.typed
wat/version.py
wat/inspection/__init__.py
wat/inspection/inspection.py
wat-0.7.0.dist-info/licenses/LICENSE
wat-0.7.0.dist-info/METADATA
wat-0.7.0.dist-info/WHEEL
wat-0.7.0.dist-info/top_level.txt
wat-0.7.0.dist-info/RECORD
