Metadata-Version: 2.4
Name: wat
Version: 0.7.0
Summary: Deep inspection of Python objects
Author-email: igrek51 <igrek51.dev@gmail.com>
License-Expression: MIT
Project-URL: Homepage, https://github.com/igrek51/wat
Classifier: Programming Language :: Python :: 3
Classifier: Operating System :: OS Independent
Requires-Python: >=3.8
License-File: LICENSE
Dynamic: license-file
